[{"Dataset": "../data/without_stopwords/un", "Dataset Size": 50422, "Model": "BERTopic", "Params": {"embedding_model": "sentence-transformers/all-mpnet-base-v2", "nr_topics": 10, "min_topic_size": 15, "verbose": true, "calculate_probabilities": false}, "Scores": {"npmi": 0.03267800164120819, "diversity": 0.8333333333333334}, "Computation Time": 77.85853171348572}, {"Dataset": "../data/without_stopwords/un", "Dataset Size": 50422, "Model": "BERTopic", "Params": {"embedding_model": "sentence-transformers/all-mpnet-base-v2", "nr_topics": 20, "min_topic_size": 15, "verbose": true, "calculate_probabilities": false}, "Scores": {"npmi": 0.03267800164120819, "diversity": 0.8333333333333334}, "Computation Time": 76.67592144012451}, {"Dataset": "../data/without_stopwords/un", "Dataset Size": 50422, "Model": "BERTopic", "Params": {"embedding_model": "sentence-transformers/all-mpnet-base-v2", "nr_topics": 30, "min_topic_size": 15, "verbose": true, "calculate_probabilities": false}, "Scores": {"npmi": 0.03267800164120819, "diversity": 0.8333333333333334}, "Computation Time": 77.07754492759705}, {"Dataset": "../data/without_stopwords/un", "Dataset Size": 50422, "Model": "BERTopic", "Params": {"embedding_model": "sentence-transformers/all-mpnet-base-v2", "nr_topics": 40, "min_topic_size": 15, "verbose": true, "calculate_probabilities": false}, "Scores": {"npmi": 0.03267800164120819, "diversity": 0.8333333333333334}, "Computation Time": 76.89089107513428}, {"Dataset": "../data/without_stopwords/un", "Dataset Size": 50422, "Model": "BERTopic", "Params": {"embedding_model": "sentence-transformers/all-mpnet-base-v2", "nr_topics": 50, "min_topic_size": 15, "verbose": true, "calculate_probabilities": false}, "Scores": {"npmi": 0.03267800164120819, "diversity": 0.8333333333333334}, "Computation Time": 76.48280835151672}]