[{"Dataset": "../data/without_stopwords/un", "Dataset Size": 50422, "Model": "BERTopic", "Params": {"embedding_model": "sentence-transformers/all-mpnet-base-v2", "nr_topics": 10, "min_topic_size": 15, "verbose": true, "calculate_probabilities": false}, "Scores": {"npmi": 0.08907862078551314, "diversity": 0.8222222222222222}, "Computation Time": 75.59458613395691}, {"Dataset": "../data/without_stopwords/un", "Dataset Size": 50422, "Model": "BERTopic", "Params": {"embedding_model": "sentence-transformers/all-mpnet-base-v2", "nr_topics": 20, "min_topic_size": 15, "verbose": true, "calculate_probabilities": false}, "Scores": {"npmi": 0.09957894024179362, "diversity": 0.7631578947368421}, "Computation Time": 75.12135076522827}, {"Dataset": "../data/without_stopwords/un", "Dataset Size": 50422, "Model": "BERTopic", "Params": {"embedding_model": "sentence-transformers/all-mpnet-base-v2", "nr_topics": 30, "min_topic_size": 15, "verbose": true, "calculate_probabilities": false}, "Scores": {"npmi": 0.1185197322562915, "diversity": 0.7827586206896552}, "Computation Time": 75.37459063529968}, {"Dataset": "../data/without_stopwords/un", "Dataset Size": 50422, "Model": "BERTopic", "Params": {"embedding_model": "sentence-transformers/all-mpnet-base-v2", "nr_topics": 40, "min_topic_size": 15, "verbose": true, "calculate_probabilities": false}, "Scores": {"npmi": 0.13571993076194874, "diversity": 0.764102564102564}, "Computation Time": 74.50891971588135}, {"Dataset": "../data/without_stopwords/un", "Dataset Size": 50422, "Model": "BERTopic", "Params": {"embedding_model": "sentence-transformers/all-mpnet-base-v2", "nr_topics": 50, "min_topic_size": 15, "verbose": true, "calculate_probabilities": false}, "Scores": {"npmi": 0.12998963378288486, "diversity": 0.7551020408163265}, "Computation Time": 74.59312868118286}]