[{"Dataset": "../data/bbc_news", "Dataset Size": 2225, "Model": "BERTopic", "Params": {"embedding_model": "sentence-transformers/all-mpnet-base-v2", "nr_topics": 10, "min_topic_size": 15, "verbose": true, "calculate_probabilities": false}, "Scores": {"npmi": 0.17419308304980807, "diversity": 0.8555555555555555}, "Computation Time": 13.651970863342285}, {"Dataset": "../data/bbc_news", "Dataset Size": 2225, "Model": "BERTopic", "Params": {"embedding_model": "sentence-transformers/all-mpnet-base-v2", "nr_topics": 20, "min_topic_size": 15, "verbose": true, "calculate_probabilities": false}, "Scores": {"npmi": 0.16732409988682306, "diversity": 0.7842105263157895}, "Computation Time": 14.307067155838013}, {"Dataset": "../data/bbc_news", "Dataset Size": 2225, "Model": "BERTopic", "Params": {"embedding_model": "sentence-transformers/all-mpnet-base-v2", "nr_topics": 30, "min_topic_size": 15, "verbose": true, "calculate_probabilities": false}, "Scores": {"npmi": 0.16732409988682306, "diversity": 0.7842105263157895}, "Computation Time": 13.567542314529419}, {"Dataset": "../data/bbc_news", "Dataset Size": 2225, "Model": "BERTopic", "Params": {"embedding_model": "sentence-transformers/all-mpnet-base-v2", "nr_topics": 40, "min_topic_size": 15, "verbose": true, "calculate_probabilities": false}, "Scores": {"npmi": 0.16732409988682306, "diversity": 0.7842105263157895}, "Computation Time": 13.228848934173584}, {"Dataset": "../data/bbc_news", "Dataset Size": 2225, "Model": "BERTopic", "Params": {"embedding_model": "sentence-transformers/all-mpnet-base-v2", "nr_topics": 50, "min_topic_size": 15, "verbose": true, "calculate_probabilities": false}, "Scores": {"npmi": 0.16732409988682306, "diversity": 0.7842105263157895}, "Computation Time": 13.81730604171753}]