[{"Dataset": "../data/bbc_news", "Dataset Size": 2225, "Model": "BERTopic", "Params": {"embedding_model": "sentence-transformers/all-mpnet-base-v2", "nr_topics": 10, "min_topic_size": 15, "verbose": true, "calculate_probabilities": false}, "Scores": {"npmi": 0.15457265465954362, "diversity": 0.92}, "Computation Time": 24.01862359046936}, {"Dataset": "../data/bbc_news", "Dataset Size": 2225, "Model": "BERTopic", "Params": {"embedding_model": "sentence-transformers/all-mpnet-base-v2", "nr_topics": 20, "min_topic_size": 15, "verbose": true, "calculate_probabilities": false}, "Scores": {"npmi": 0.15457265465954362, "diversity": 0.92}, "Computation Time": 23.34044051170349}, {"Dataset": "../data/bbc_news", "Dataset Size": 2225, "Model": "BERTopic", "Params": {"embedding_model": "sentence-transformers/all-mpnet-base-v2", "nr_topics": 30, "min_topic_size": 15, "verbose": true, "calculate_probabilities": false}, "Scores": {"npmi": 0.15457265465954362, "diversity": 0.92}, "Computation Time": 23.74580717086792}, {"Dataset": "../data/bbc_news", "Dataset Size": 2225, "Model": "BERTopic", "Params": {"embedding_model": "sentence-transformers/all-mpnet-base-v2", "nr_topics": 40, "min_topic_size": 15, "verbose": true, "calculate_probabilities": false}, "Scores": {"npmi": 0.15457265465954362, "diversity": 0.92}, "Computation Time": 24.534458875656128}, {"Dataset": "../data/bbc_news", "Dataset Size": 2225, "Model": "BERTopic", "Params": {"embedding_model": "sentence-transformers/all-mpnet-base-v2", "nr_topics": 50, "min_topic_size": 15, "verbose": true, "calculate_probabilities": false}, "Scores": {"npmi": 0.15457265465954362, "diversity": 0.92}, "Computation Time": 23.708956003189087}]