[{"Dataset": "../data/un", "Dataset Size": 50422, "Model": "BERTopic", "Params": {"embedding_model": "sentence-transformers/all-mpnet-base-v2", "nr_topics": 10, "min_topic_size": 15, "verbose": true, "calculate_probabilities": false}, "Scores": {"npmi": 0.04812484126769875, "diversity": 0.6777777777777778}, "Computation Time": 79.56448078155518}, {"Dataset": "../data/un", "Dataset Size": 50422, "Model": "BERTopic", "Params": {"embedding_model": "sentence-transformers/all-mpnet-base-v2", "nr_topics": 20, "min_topic_size": 15, "verbose": true, "calculate_probabilities": false}, "Scores": {"npmi": 0.05659264436831566, "diversity": 0.6210526315789474}, "Computation Time": 79.77724409103394}, {"Dataset": "../data/un", "Dataset Size": 50422, "Model": "BERTopic", "Params": {"embedding_model": "sentence-transformers/all-mpnet-base-v2", "nr_topics": 30, "min_topic_size": 15, "verbose": true, "calculate_probabilities": false}, "Scores": {"npmi": 0.06406224666642711, "diversity": 0.6068965517241379}, "Computation Time": 80.37064504623413}, {"Dataset": "../data/un", "Dataset Size": 50422, "Model": "BERTopic", "Params": {"embedding_model": "sentence-transformers/all-mpnet-base-v2", "nr_topics": 40, "min_topic_size": 15, "verbose": true, "calculate_probabilities": false}, "Scores": {"npmi": 0.07570740328349257, "diversity": 0.6384615384615384}, "Computation Time": 80.74673104286194}, {"Dataset": "../data/un", "Dataset Size": 50422, "Model": "BERTopic", "Params": {"embedding_model": "sentence-transformers/all-mpnet-base-v2", "nr_topics": 50, "min_topic_size": 15, "verbose": true, "calculate_probabilities": false}, "Scores": {"npmi": 0.08027350294500668, "diversity": 0.6448979591836734}, "Computation Time": 80.88416314125061}]